{
	"info": {
		"_postman_id": "82f62c5b-9ebe-40d1-a3b9-8fc06ccd2c81",
		"name": "vota-talesb-api",
		"schema": "https://schema.getpostman.com/json/collection/v2.1.0/collection.json"
	},
	"item": [
		{
			"name": "Candidato",
			"item": [
				{
					"name": "Obter Candidatos",
					"request": {
						"method": "GET",
						"header": [],
						"url": {
							"raw": "localhost:8080/api/candidato",
							"host": [
								"localhost"
							],
							"port": "8080",
							"path": [
								"api",
								"candidato"
							]
						}
					},
					"response": []
				},
				{
					"name": "Obter Candidatos Por Eleicao",
					"request": {
						"method": "GET",
						"header": [],
						"url": {
							"raw": "localhost:8080/api/candidato/eleicao/1",
							"host": [
								"localhost"
							],
							"port": "8080",
							"path": [
								"api",
								"candidato",
								"eleicao",
								"1"
							]
						}
					},
					"response": []
				},
				{
					"name": "Novo Candidato",
					"request": {
						"method": "POST",
						"header": [],
						"body": {
							"mode": "raw",
							"raw": "{\n    \"numero\":\"6545\",\n    \"nome\":\"Candidato N\",\n    \"eleicaoId\":1\n}",
							"options": {
								"raw": {
									"language": "json"
								}
							}
						},
						"url": {
							"raw": "localhost:8080/api/candidato",
							"host": [
								"localhost"
							],
							"port": "8080",
							"path": [
								"api",
								"candidato"
							]
						}
					},
					"response": []
				},
				{
					"name": "Obter Candidato",
					"request": {
						"method": "GET",
						"header": [],
						"url": {
							"raw": "localhost:8080/api/candidato/10",
							"host": [
								"localhost"
							],
							"port": "8080",
							"path": [
								"api",
								"candidato",
								"10"
							]
						}
					},
					"response": []
				},
				{
					"name": "Remover Candidato",
					"request": {
						"method": "DELETE",
						"header": [],
						"url": {
							"raw": "localhost:8080/api/candidato/2",
							"host": [
								"localhost"
							],
							"port": "8080",
							"path": [
								"api",
								"candidato",
								"2"
							]
						}
					},
					"response": []
				}
			]
		},
		{
			"name": "Eleição",
			"item": [
				{
					"name": "Obter Eleições",
					"request": {
						"method": "GET",
						"header": [],
						"url": {
							"raw": "localhost:8080/api/eleicao",
							"host": [
								"localhost"
							],
							"port": "8080",
							"path": [
								"api",
								"eleicao"
							]
						}
					},
					"response": []
				},
				{
					"name": "Obter Eleição",
					"request": {
						"method": "GET",
						"header": [],
						"url": {
							"raw": "localhost:8080/api/eleicao/1",
							"host": [
								"localhost"
							],
							"port": "8080",
							"path": [
								"api",
								"eleicao",
								"1"
							]
						}
					},
					"response": []
				},
				{
					"name": "Remover Eleição",
					"request": {
						"method": "DELETE",
						"header": [],
						"url": {
							"raw": "localhost:8080/api/eleicao/5",
							"host": [
								"localhost"
							],
							"port": "8080",
							"path": [
								"api",
								"eleicao",
								"5"
							]
						}
					},
					"response": []
				},
				{
					"name": "Nova Eleição",
					"request": {
						"method": "POST",
						"header": [],
						"body": {
							"mode": "raw",
							"raw": "{\n    \"descricao\":\"eleicao teste\"\n}",
							"options": {
								"raw": {
									"language": "json"
								}
							}
						},
						"url": {
							"raw": "localhost:8080/api/eleicao",
							"host": [
								"localhost"
							],
							"port": "8080",
							"path": [
								"api",
								"eleicao"
							]
						}
					},
					"response": []
				}
			]
		},
		{
			"name": "Eleitor",
			"item": [
				{
					"name": "Obter Eleitores",
					"request": {
						"method": "GET",
						"header": [],
						"url": {
							"raw": "localhost:8080/api/eleitor",
							"host": [
								"localhost"
							],
							"port": "8080",
							"path": [
								"api",
								"eleitor"
							]
						}
					},
					"response": []
				},
				{
					"name": "Obter Eleitor",
					"request": {
						"method": "GET",
						"header": [],
						"url": {
							"raw": "localhost:8080/api/eleitor/5",
							"host": [
								"localhost"
							],
							"port": "8080",
							"path": [
								"api",
								"eleitor",
								"5"
							]
						}
					},
					"response": []
				},
				{
					"name": "Remover Eleitor",
					"request": {
						"method": "DELETE",
						"header": [],
						"url": {
							"raw": "localhost:8080/api/eleitor/6",
							"host": [
								"localhost"
							],
							"port": "8080",
							"path": [
								"api",
								"eleitor",
								"6"
							]
						}
					},
					"response": []
				},
				{
					"name": "Novo eleitor",
					"request": {
						"method": "POST",
						"header": [],
						"body": {
							"mode": "raw",
							"raw": "{\n    \"codigo\":\"Eleitor API Codigo\",\n    \"nome\":\"Eleitor Api nome\",\n    \"email\":\"eleitorapiemail@email.com\",\n    \"telefone\":\"21999999\",\n    \"token\":\"123123-54-5454\"\n}",
							"options": {
								"raw": {
									"language": "json"
								}
							}
						},
						"url": {
							"raw": "localhost:8080/api/eleitor",
							"host": [
								"localhost"
							],
							"port": "8080",
							"path": [
								"api",
								"eleitor"
							]
						}
					},
					"response": []
				}
			]
		},
		{
			"name": "Voto",
			"item": [
				{
					"name": "Obter Votos",
					"request": {
						"method": "GET",
						"header": [],
						"url": {
							"raw": "localhost:8080/api/voto",
							"host": [
								"localhost"
							],
							"port": "8080",
							"path": [
								"api",
								"voto"
							]
						}
					},
					"response": []
				},
				{
					"name": "Obter Votos Por Eleicao",
					"request": {
						"method": "GET",
						"header": [],
						"url": {
							"raw": "localhost:8080/api/voto/eleicao/3",
							"host": [
								"localhost"
							],
							"port": "8080",
							"path": [
								"api",
								"voto",
								"eleicao",
								"3"
							]
						}
					},
					"response": []
				},
				{
					"name": "Obter Voto",
					"request": {
						"method": "GET",
						"header": [],
						"url": {
							"raw": "localhost:8080/api/voto/12",
							"host": [
								"localhost"
							],
							"port": "8080",
							"path": [
								"api",
								"voto",
								"12"
							]
						}
					},
					"response": []
				},
				{
					"name": "Remover Voto",
					"request": {
						"method": "DELETE",
						"header": [],
						"url": {
							"raw": "localhost:8080/api/voto/12",
							"host": [
								"localhost"
							],
							"port": "8080",
							"path": [
								"api",
								"voto",
								"12"
							]
						}
					},
					"response": []
				},
				{
					"name": "Novo voto",
					"request": {
						"method": "POST",
						"header": [],
						"body": {
							"mode": "raw",
							"raw": "{\n    \"eleitorId\":5,\n    \"eleicaoId\":1,\n    \"candidatoId\":10,\n    \"localizacao\":\"Mesquita\"\n}",
							"options": {
								"raw": {
									"language": "json"
								}
							}
						},
						"url": {
							"raw": "localhost:8080/api/voto",
							"host": [
								"localhost"
							],
							"port": "8080",
							"path": [
								"api",
								"voto"
							]
						}
					},
					"response": []
				}
			]
		}
	]
}